ET_Client.py
FuelSDK/__init__.py
FuelSDK/client.py
FuelSDK/objects.py
FuelSDK/rest.py
FuelSDK/suds_patch.py
Salesforce_FuelSDK_Sans-1.3.1.dist-info/LICENSE
Salesforce_FuelSDK_Sans-1.3.1.dist-info/METADATA
Salesforce_FuelSDK_Sans-1.3.1.dist-info/WHEEL
Salesforce_FuelSDK_Sans-1.3.1.dist-info/top_level.txt
Salesforce_FuelSDK_Sans-1.3.1.dist-info/RECORD
