Metadata-Version: 2.1
Name: Salesforce-FuelSDK-Sans
Version: 1.3.1
Summary: Salesforce Marketing Cloud Fuel SDK for Python
Home-page: https://github.com/seahawks8/FuelSDK-Python
Author: Seahawks8
License: MIT
Classifier: Development Status :: 4 - Beta
Classifier: Intended Audience :: Developers
Classifier: License :: OSI Approved :: MIT License
Classifier: Operating System :: OS Independent
Classifier: Topic :: Software Development :: Libraries
Classifier: Programming Language :: Python :: 3.7
Requires-Python: >=3
License-File: LICENSE
Requires-Dist: PyJWT (>=2.4.0)
Requires-Dist: requests (>=2.28.0)
Requires-Dist: suds-community (>=1.1.1)
